[
  {
    "title": "Vintage Camera",
    "image": "https://example.com/images/camera.jpg",
    "url": "https://example.com/vintage-camera",
    "price": {
      "value": 150,
      "currency": "USD"
    },
    "date": "2024-03-01",
    "location": "New York, NY",
    "platform": "ebay",
    "condition": "Used",
    "quantitySold": 1,
    "sellerCount": 1
  },
  {
    "title": "Retro Game Console",
    "image": "https://example.com/images/console.jpg",
    "url": "https://example.com/retro-console",
    "price": {
      "value": 80,
      "currency": "USD"
    },
    "date": "2024-02-15",
    "location": "Los Angeles, CA",
    "platform": "tcgplayer",
    "condition": "Near Mint",
    "quantitySold": 2,
    "sellerCount": null
  }
]
